{
  "db_name": "PostgreSQL",
  "query": "SELECT * FROM connections WHERE user_id = $1",
  "describe": {
    "columns": [
      {
        "ordinal": 0,
        "name": "user_id",
        "type_info": "Uuid"
      },
      {
        "ordinal": 1,
        "name": "created_at",
        "type_info": "Timestamp"
      },
      {
        "ordinal": 2,
        "name": "conn_user_id",
        "type_info": "Int8"
      },
      {
        "ordinal": 3,
        "name": "username",
        "type_info": "Varchar"
      },
      {
        "ordinal": 4,
        "name": "display_name",
        "type_info": "Varchar"
      }
    ],
    "parameters": {
      "Left": [
        "Uuid"
      ]
    },
    "nullable": [
      false,
      false,
      false,
      false,
      false
    ]
  },
  "hash": "1edf516961b17eab5c325974a4152414b40aeac27c84be0a98d6127ef7940d55"
}
